test_utils/__init__.py
test_utils/aerospike_client.py
test_utils/aws.py
test_utils/cassandra.py
test_utils/common.py
test_utils/jenkins.py
test_utils/jfrog.py
test_utils/k8.py
test_utils/kafka_client.py
test_utils/logger.py
test_utils/mysql.py
test_utils/postgresql.py
test_utils/redis.py
test_utils/testrail.py
test_utils/voltdb_client.py
core_test_utils-1.0.0.dist-info/METADATA
core_test_utils-1.0.0.dist-info/WHEEL
core_test_utils-1.0.0.dist-info/top_level.txt
core_test_utils-1.0.0.dist-info/RECORD
