Metadata-Version: 2.1
Name: core-test-utils
Version: 1.0.0
Summary: Test utils library for python frameworks
Home-page: https://github.com/sarvesh371/test-utils
Author: Sarvesh Singh
Author-email: sarveshsingh.03@gmail.com
Project-URL: Bug Tracker, https://github.com/sarvesh371/test-utils/issues
Classifier: Programming Language :: Python :: 3
Classifier: License :: OSI Approved :: MIT License
Classifier: Operating System :: OS Independent
Requires-Python: >=3.6
Requires-Dist: aerospike (==4.0.0)
Requires-Dist: allure-pytest (==2.8.29)
Requires-Dist: botocore (==1.23.15)
Requires-Dist: boto3 (==1.20.15)
Requires-Dist: cassandra-driver (==3.25.0)
Requires-Dist: Faker (==4.1.2)
Requires-Dist: kafka-python (==2.0.2)
Requires-Dist: kubernetes (==22.6.0)
Requires-Dist: mysql-connector-python (==8.0.27)
Requires-Dist: psycopg2 (==2.9.3)
Requires-Dist: psycopg2-binary (==2.9.3)
Requires-Dist: pytz (==2020.1)
Requires-Dist: PyYAML (==6.0)
Requires-Dist: redis (==4.2.2)
Requires-Dist: requests (==2.24.0)
Requires-Dist: testrail-api (==1.10.3)
